reactango_cli/__init__.py
reactango_cli/cli.py
reactango-1.2.0.dist-info/METADATA
reactango-1.2.0.dist-info/WHEEL
reactango-1.2.0.dist-info/entry_points.txt
reactango-1.2.0.dist-info/top_level.txt
reactango-1.2.0.dist-info/RECORD
