Metadata-Version: 2.4
Name: reactango
Version: 1.2.0
Summary: A CLI tool that simplify React and Django Implementation.
Author-email: Muhammad Abdullah <muhmmadabdullah6346@gmail.com>
Project-URL: Homepage, https://github.com/Abdullah6346/ReacTango-v1
Project-URL: Bug Tracker, https://github.com/Abdullah6346/ReacTango-v1/issues
Project-URL: Repository, https://github.com/Abdullah6346/ReacTango-v1
Classifier: Development Status :: 4 - Beta
Classifier: Intended Audience :: Developers
Classifier: License :: OSI Approved :: MIT License
Classifier: Operating System :: OS Independent
Classifier: Programming Language :: Python :: 3
Classifier: Topic :: Software Development :: Build Tools
Classifier: Topic :: Utilities
Requires-Python: >=3.7
Requires-Dist: questionary<2.0.0,>=1.10.0
